Cargo.toml
LICENSE.txt
naluacq-0.4.10.dist-info/METADATA
naluacq-0.4.10.dist-info/WHEEL
naluacq-0.4.10.dist-info/licenses/LICENSE.txt
naluacq/__init__.py
naluacq/__init__.pyi
naluacq/naluacq.cpython-310-aarch64-linux-gnu.so
naluacq/py.typed
naluacq-0.4.10.dist-info/RECORD
