Metadata-Version: 2.4
Name: naluacq
Version: 0.4.10
License-File: LICENSE.txt
Summary: Python bindings for the Nalu acquisition system
Author: Mitchell Matsumori-Kelly <mitchell@naluscientific.com>
Author-email: Marcus Luck <marcus@naluscientific.com>
License: LGPL-3.0-or-later
Requires-Python: >=3.8
Project-URL: Source Code, https://github.com/NaluScientific/naluacq
